tvts/__init__.py
tvts/tvts.py
tvts/tvts_locate_service.py
tvts/examples/__init__.py
tvts/examples/x050_remote_locate_service_test.py
tvts/examples/x100_fake_demo_simple.py
tvts/examples/x150_fake_demo_simple_with_old_train_id.py
tvts/examples/x200_fake_demo_samulating_practice.py
tvts/examples/x250_mlp_torch_mnist_tvts.py
tvts/examples/x300_vgg16_tf2_cifar10_tvts.py
tvts/examples/x400_vgg16_torch_cifar10_tvts.py
tvts/examples/x450_vgg16_torch_DP_cifar10_tvts.py
tvts/examples/x500_vgg16_torch_DDP_cifar10_tvts.py
tvts/examples/x525_vgg16_torch_DDP_spawn_cifar10_tvts.py
tvts/examples/x550_vgg16_torch_DDP_KV_cifar10_tvts.py
tvts/examples/x600_vgg16_torch_model_parallel_cifar10_tvts.py
tvts/examples/x650_vgg16_torch_model_parallel_check.py
tvts/examples/x700_vgg16_torch_accelerate_cifar10_tvts.py
tvts-0.0.1.1.dist-info/COPYING
tvts-0.0.1.1.dist-info/LICENSE
tvts-0.0.1.1.dist-info/METADATA
tvts-0.0.1.1.dist-info/WHEEL
tvts-0.0.1.1.dist-info/top_level.txt
tvts-0.0.1.1.dist-info/RECORD
