Metadata-Version: 2.2
Name: tvts
Version: 0.0.1.1
Summary: TVTS (Trackable and Visible Training System) is an auxiliary system for machine learning or deep learning model training written in Python3, with MongoDB as its storage backend and Matplotlib as its visualization backend.
Author-email: Yun-Peng Pei <belarc@163.com>
License: 
Project-URL: Homepage, https://github.com/cmpltrtok20/tvts
Project-URL: Issues, https://github.com/cmpltrtok20/tvts/issues
Classifier: Programming Language :: Python :: 3
Classifier: Operating System :: POSIX :: Linux
Requires-Python: >=3.8
License-File: LICENSE
License-File: COPYING
